adafruit_veml6070.py
adafruit_circuitpython_veml6070-3.1.25.dist-info/licenses/LICENSE
adafruit_circuitpython_veml6070-3.1.25.dist-info/METADATA
adafruit_circuitpython_veml6070-3.1.25.dist-info/WHEEL
adafruit_circuitpython_veml6070-3.1.25.dist-info/top_level.txt
adafruit_circuitpython_veml6070-3.1.25.dist-info/RECORD
